Metadata-Version: 2.4
Name: structx-llm
Version: 0.4.9
Summary: Structured data extraction from text using LLMs and dynamic model generation
Author-email: blacksuan19 <py@blacksuan19.dev>
Classifier: Development Status :: 5 - Production/Stable
Classifier: Framework :: AsyncIO
Classifier: Framework :: Pydantic
Classifier: Intended Audience :: Developers
Classifier: Operating System :: OS Independent
Classifier: Programming Language :: Python :: 3.10
Classifier: Programming Language :: Python :: 3.11
Classifier: Programming Language :: Python :: 3.12
Classifier: Programming Language :: Python :: 3.9
Classifier: Programming Language :: Python :: 3
Classifier: Topic :: Database
Classifier: Topic :: Documentation
Classifier: Topic :: Internet :: WWW/HTTP :: Dynamic Content
Classifier: Topic :: Office/Business
Classifier: Topic :: Scientific/Engineering :: Artificial Intelligence
Classifier: Topic :: Scientific/Engineering :: Information Analysis
Classifier: Topic :: Software Development :: Libraries :: Python Modules
Classifier: Topic :: Software Development :: Libraries
Classifier: Topic :: Text Processing :: Linguistic
Classifier: Topic :: Text Processing :: Markup
Classifier: Topic :: Text Processing
Classifier: Topic :: Utilities
Classifier: Typing :: Typed
Requires-Python: >=3.10
License-File: LICENSE
Requires-Dist: structx>=0.4.7
Provides-Extra: dev
Requires-Dist: black; extra == "dev"
Requires-Dist: bumpver; extra == "dev"
Requires-Dist: pip-tools; extra == "dev"
Requires-Dist: wheel; extra == "dev"
Provides-Extra: pdf
Requires-Dist: pypdf2; extra == "pdf"
Requires-Dist: instructor[multimodal]; extra == "pdf"
Requires-Dist: weasyprint; extra == "pdf"
Requires-Dist: markdown; extra == "pdf"
Provides-Extra: docx
Requires-Dist: python-docx; extra == "docx"
Requires-Dist: docling; extra == "docx"
Requires-Dist: markdown; extra == "docx"
Requires-Dist: weasyprint; extra == "docx"
Provides-Extra: docs
Requires-Dist: pypdf2; extra == "docs"
Requires-Dist: python-docx; extra == "docs"
Requires-Dist: instructor[multimodal]; extra == "docs"
Requires-Dist: docling; extra == "docs"
Requires-Dist: weasyprint; extra == "docs"
Requires-Dist: markdown; extra == "docs"
Provides-Extra: unstructured
Requires-Dist: unstructured[all-docs]; extra == "unstructured"
Provides-Extra: docling
Requires-Dist: docling; extra == "docling"
Requires-Dist: markdown; extra == "docling"
Requires-Dist: weasyprint; extra == "docling"
Provides-Extra: advanced
Requires-Dist: pypdf2; extra == "advanced"
Requires-Dist: python-docx; extra == "advanced"
Requires-Dist: instructor[multimodal]; extra == "advanced"
Requires-Dist: docling; extra == "advanced"
Requires-Dist: weasyprint; extra == "advanced"
Requires-Dist: markdown; extra == "advanced"
Requires-Dist: unstructured[all-docs]; extra == "advanced"
Provides-Extra: mkdocs
Requires-Dist: mkdocs; extra == "mkdocs"
Requires-Dist: mkdocs-material; extra == "mkdocs"
Requires-Dist: mkdocstrings[markdown]; extra == "mkdocs"
Requires-Dist: mkdocstrings[python]; extra == "mkdocs"
Requires-Dist: mkdocs-git-revision-date-localized-plugin; extra == "mkdocs"
Requires-Dist: mkdocs-material[imaging]; extra == "mkdocs"
Requires-Dist: mkdocs-mermaid2-plugin; extra == "mkdocs"
Dynamic: license-file
